ABC_GP_IPM/__init__.py
ABC_GP_IPM/abc_gp_ipm.py
ABC_GP_IPM/cache.py
ABC_GP_IPM/calculate_ss.py
ABC_GP_IPM/gp_cachebasic.py
ABC_GP_IPM/gp_ipm.py
abc_gp_ipm-0.0.1.dist-info/METADATA
abc_gp_ipm-0.0.1.dist-info/WHEEL
abc_gp_ipm-0.0.1.dist-info/top_level.txt
abc_gp_ipm-0.0.1.dist-info/RECORD
