Metadata-Version: 2.1
Name: abc-gp-ipm
Version: 0.0.1
Summary: A simple Python package for implenmenting customised ABC-PMC sampling method and GP models in IPMs.
Author: Zhixiao Zhu
Classifier: Programming Language :: Python :: 3
Classifier: License :: OSI Approved :: MIT License
Classifier: Operating System :: OS Independent
Requires-Python: >=3.8
Requires-Dist: gpflow ==2.9.0
